yadumair/__init__.py
yadumair/client.py
yadumair-0.1.0.dist-info/METADATA
yadumair-0.1.0.dist-info/WHEEL
yadumair-0.1.0.dist-info/top_level.txt
yadumair-0.1.0.dist-info/RECORD
